telepythy/__init__.py
telepythy/__main__.py
telepythy/pack.py
telepythy/telepythy_service.pyz
telepythy/gui/__main__.py
telepythy/gui/about.py
telepythy/gui/config.py
telepythy/gui/control.py
telepythy/gui/document.py
telepythy/gui/highlighter.py
telepythy/gui/history.py
telepythy/gui/lexer.py
telepythy/gui/output.py
telepythy/gui/profiles.py
telepythy/gui/resources_rc.py
telepythy/gui/sconfig.py
telepythy/gui/settings.py
telepythy/gui/source.py
telepythy/gui/styles.py
telepythy/gui/textedit.py
telepythy/gui/tips.py
telepythy/gui/utils.py
telepythy/gui/window.py
telepythy/lib/__init__.py
telepythy/lib/__main__.py
telepythy/lib/event_handlers.py
telepythy/lib/interpreter.py
telepythy/lib/logs.py
telepythy/lib/service.py
telepythy/lib/sockio.py
telepythy/lib/utils.py
telepythy-0.5.4.dist-info/METADATA
telepythy-0.5.4.dist-info/WHEEL
telepythy-0.5.4.dist-info/entry_points.txt
telepythy-0.5.4.dist-info/top_level.txt
telepythy-0.5.4.dist-info/RECORD
