Metadata-Version: 2.2
Name: telepythy
Version: 0.5.4
Summary: An embeddable, remote-capable Python shell
Home-page: https://github.com/dhagrow/telepythy
Author: Miguel Turner
Author-email: cymrow@gmail.com
License: MIT
Classifier: Development Status :: 4 - Beta
Classifier: Intended Audience :: Developers
Classifier: License :: OSI Approved :: MIT License
Classifier: Programming Language :: Python :: 2
Classifier: Programming Language :: Python :: 3
Classifier: Operating System :: OS Independent
Classifier: Topic :: Software Development :: Interpreters
Classifier: Topic :: Utilities
Requires-Dist: colorlog>=6.7.0
Requires-Dist: mistune>=3.0.1
Requires-Dist: platformdirs>=3.9.1
Requires-Dist: Pygments>=2.15.1
Requires-Dist: pyqtdarktheme>=2.1.0
Requires-Dist: PySide6-Essentials>=6.5.2
Requires-Dist: QtPy>=2.3.1
Requires-Dist: shiboken6>=6.5.2
Requires-Dist: snekcfg>=0.1.1
Dynamic: author
Dynamic: author-email
Dynamic: classifier
Dynamic: description
Dynamic: description-content-type
Dynamic: home-page
Dynamic: license
Dynamic: requires-dist
Dynamic: summary
